zenora/__init__.py
zenora/client.py
zenora/deserializers.py
zenora/errors.py
zenora/exceptions.py
zenora/request.py
zenora/routes.py
zenora/utils.py
zenora/api/__init__.py
zenora/api/oauthapi.py
zenora/api/userapi.py
zenora/impl/__init__.py
zenora/impl/oauthapi.py
zenora/impl/userapi.py
zenora/models/channel.py
zenora/models/connection.py
zenora/models/guild.py
zenora/models/integration.py
zenora/models/oauth.py
zenora/models/snowflake.py
zenora/models/user.py
Zenora-0.0.3.dist-info/LICENSE
Zenora-0.0.3.dist-info/METADATA
Zenora-0.0.3.dist-info/WHEEL
Zenora-0.0.3.dist-info/top_level.txt
Zenora-0.0.3.dist-info/RECORD
