Metadata-Version: 2.1
Name: Zenora
Version: 0.0.3
Summary: A simple to use synchronous Discord REST API wrapper for Python
Home-page: https://github.com/ahnaf-zamil/zenora
Author: DevGuyAhnaf
Author-email: ahnaf@ahnafzamil.com
License: MIT
Platform: UNKNOWN
Classifier: License :: OSI Approved :: MIT License
Classifier: Operating System :: OS Independent
Classifier: Programming Language :: Python :: 3
Classifier: Programming Language :: Python :: 3.8
Classifier: Programming Language :: Python :: 3.9
Requires-Python: >=3.8
Requires-Dist: attrs
Requires-Dist: requests
